setup.py
hackerspacepi/__init__.py
hackerspacepi.egg-info/PKG-INFO
hackerspacepi.egg-info/SOURCES.txt
hackerspacepi.egg-info/dependency_links.txt
hackerspacepi.egg-info/entry_points.txt
hackerspacepi.egg-info/not-zip-safe
hackerspacepi.egg-info/requires.txt
hackerspacepi.egg-info/top_level.txt