Metadata-Version: 1.1
Name: hackerspacepi
Version: 0.1.8
Summary: SpaceAPI compliant service written in python3.5
Home-page: https://github.com/XayOn/HackerspacePI
Author: David Francos Cuartero
Author-email: me@davidfrancos.net
License: BSD
Keywords: hackerspacepi
Platform: UNKNOWN
Classifier: Development Status :: 2 - Pre-Alpha
Classifier: Intended Audience :: Developers
Classifier: License :: OSI Approved :: BSD License
Classifier: Natural Language :: English
Classifier: Programming Language :: Python :: 2
Classifier: Programming Language :: Python :: 2.6
Classifier: Programming Language :: Python :: 2.7
Classifier: Programming Language :: Python :: 3
Classifier: Programming Language :: Python :: 3.3
Classifier: Programming Language :: Python :: 3.4
